terminalmaze/__init__.py
terminalmaze/algorithms/__init__.py
terminalmaze/algorithms/algorithm.py
terminalmaze/algorithms/gen/__init__.py
terminalmaze/algorithms/gen/aldousbroder.py
terminalmaze/algorithms/gen/binarytree.py
terminalmaze/algorithms/gen/ellers.py
terminalmaze/algorithms/gen/huntandkill.py
terminalmaze/algorithms/gen/kruskalsrandomized.py
terminalmaze/algorithms/gen/primssimple.py
terminalmaze/algorithms/gen/primsweighted.py
terminalmaze/algorithms/gen/recursivebacktracker.py
terminalmaze/algorithms/gen/recursivedivision.py
terminalmaze/algorithms/gen/sidewinder.py
terminalmaze/algorithms/gen/wilsons.py
terminalmaze/algorithms/solve/__init__.py
terminalmaze/algorithms/solve/breadthfirst.py
terminalmaze/algorithms/solve/greedybestfirst.py
terminalmaze/config/__init__.py
terminalmaze/config/masks/terminalmaze.mask
terminalmaze/config/masks/terminalmaze_bound.mask
terminalmaze/config/masks/terminalmaze_inverted.mask
terminalmaze/config/themes/default.toml
terminalmaze/config/themes/hextoxterm.py
terminalmaze/main.py
terminalmaze/resources/__init__.py
terminalmaze/resources/cell.py
terminalmaze/resources/grid.py
terminalmaze/visual/__init__.py
terminalmaze/visual/ansitools.py
terminalmaze/visual/colorterm.py
terminalmaze/visual/visualeffects.py
terminalmaze/visual/visualmaze.py
terminalmaze-0.1.0.dist-info/WHEEL
terminalmaze-0.1.0.dist-info/entry_points.txt
terminalmaze-0.1.0.dist-info/METADATA
terminalmaze-0.1.0.dist-info/RECORD
