Metadata-Version: 2.3
Name: terminalmaze
Version: 0.1.0
Summary: Maze generation visualizer.
Author: Chris
Author-email: Chris <741258+github@pm.me>
Requires-Dist: pydantic>=2.12.4
Requires-Dist: tomli>=2.3.0
Requires-Python: >=3.10
